ironsnake_simple-0.1.0.dist-info/METADATA
ironsnake_simple-0.1.0.dist-info/WHEEL
ironsnake_simple-0.1.0.dist-info/license_files/LICENSE
ironsnake/simple/__init__.py
ironsnake/simple/module1.py
ironsnake/simple/person.py
ironsnake/simple/ironsnake_simple_pyo3.pypy310-pp73-x86_64-linux-gnu.so
ironsnake_simple-0.1.0.dist-info/RECORD
